appconfig/__init__.py
appconfig/appconfig.py
appconfig_json-0.1.5.1014.dist-info/LICENSE
appconfig_json-0.1.5.1014.dist-info/METADATA
appconfig_json-0.1.5.1014.dist-info/WHEEL
appconfig_json-0.1.5.1014.dist-info/top_level.txt
appconfig_json-0.1.5.1014.dist-info/RECORD
