Metadata-Version: 2.1
Name: appconfig-json
Version: 0.1.5.1014
Summary: Package for advanced application config file in json
Home-page: https://github.com/pavelsuk/appconfig_package
Author: Pavel Suk
Author-email: pavelsuk@users.noreply.github.com
Project-URL: Bug Tracker, https://github.com/pavelsuk/appconfig_package/issues
Classifier: Programming Language :: Python :: 3.6
Classifier: License :: OSI Approved :: MIT License
Classifier: Operating System :: OS Independent
Classifier: Development Status :: 3 - Alpha
Classifier: Intended Audience :: Developers
Requires-Python: >=3.6
License-File: LICENSE
